[{"website":"https:\/\/ensis.surf\/product\/roger\/","reviews":[{"stars":3,"text":"No real low end, such a small wind strength window, no real de-power, extremely twitchy, stupid red ball where lines can tangle.\nPositive: very high performance, really nimble.","date":"2025-04-08","userName":"Nils Mango","website":"https:\/\/nilsmango.ch"}],"imageFilename":"DSC03057_by-Tobias-Meier.webp","sizes":[{"areaSqM":3,"listPriceUSD":985,"doubleSkin":false}],"discontinued":false,"videos":[{"url":"https:\/\/www.instagram.com\/reel\/DEHSDqQoJKe\/?utm_source=ig_web_copy_link&igsh=MzRlODBiNWFlZA==","date":"2025-04-03","kind":"Insta"},{"url":"https:\/\/www.youtube.com\/watch?v=9SrjRrQCFmA","date":"2025-04-07","kind":"YouTube"},{"url":"https:\/\/www.youtube.com\/watch?v=HBg6BxDoPyc","date":"2025-04-07","kind":"YouTube"},{"url":"https:\/\/www.instagram.com\/reel\/DIJhZxZRVV8\/?utm_source=ig_web_copy_link","date":"2025-04-08","kind":"Insta"}],"brandName":"ENSIS","name":"Roger"},{"website":"https:\/\/boardridingmaui.com\/pages\/parawing","reviews":[{"stars":4,"text":"Nice low end, very small to pack down.\r\nNegative: Bar is very thin and the fabric can rip at the ends.","date":"2025-04-09","userName":"Nils Mango","website":"https:\/\/nilsmango.ch"}],"imageFilename":"BRM-Maliko-123.jpg.webp","sizes":[{"areaSqM":1.8,"listPriceUSD":900,"doubleSkin":false},{"areaSqM":2.9,"listPriceUSD":975,"doubleSkin":false},{"areaSqM":4,"listPriceUSD":1050,"doubleSkin":false},{"areaSqM":5.1,"listPriceUSD":1125,"doubleSkin":false},{"areaSqM":6.2,"listPriceUSD":1200,"doubleSkin":false}],"videos":[{"url":"https:\/\/www.youtube.com\/watch?v=oEweFf1tM4s&pp=ygUKYnJtIG1hbGlrbw%3D%3D","date":"2025-04-08","kind":"YouTube"},{"url":"https:\/\/www.youtube.com\/watch?v=yQlmsyK6qMQ&pp=ygUKYnJtIG1hbGlrbw%3D%3D","date":"2025-04-08","kind":"YouTube"},{"url":"https:\/\/www.youtube.com\/watch?v=3lJtdwY5puk&t=1s&pp=ygUKYnJtIG1hbGlrb9IHCQl-CQGHKiGM7w%3D%3D","date":"2025-04-08","kind":"YouTube"},{"url":"https:\/\/www.youtube.com\/watch?v=Nch2R9zzhxk&t=530s","date":"2025-04-08","kind":"YouTube"},{"url":"https:\/\/www.youtube.com\/watch?v=29egcF9nyCM&t=251s&pp=ygURbWFsaWtvIGJybSByZXZpZXc%3D","date":"2025-04-08","kind":"YouTube"}],"brandName":"Boardriding Maui","name":"Maliko"},{"website":"https:\/\/int.takoon.com\/collections\/parawing\/products\/parawing-zenith","reviews":[],"imageFilename":"parawing-zenith_carousel-1_3024x.jpg","sizes":[{"aspectRatio":2.33,"wingSpan":2.18,"listPriceUSD":386,"weightKg":0.53,"doubleSkin":false,"areaSqM":2,"linesLengthCm":107},{"aspectRatio":2.87,"wingSpan":2.98,"listPriceUSD":425,"weightKg":0.73,"doubleSkin":false,"areaSqM":3,"linesLengthCm":145},{"aspectRatio":2.36,"wingSpan":3.08,"listPriceUSD":464,"weightKg":0.93,"doubleSkin":false,"areaSqM":4,"linesLengthCm":146},{"aspectRatio":1.96,"wingSpan":2.96,"listPriceUSD":502,"weightKg":1.13,"doubleSkin":false,"areaSqM":5,"linesLengthCm":196}],"discontinued":false,"videos":[{"url":"https:\/\/www.youtube.com\/watch?v=47Awi1U78-Q","date":"2025-04-16","kind":"YouTube"},{"url":"https:\/\/www.youtube.com\/shorts\/hBoW_sqfAuM","date":"2025-04-16","kind":"YouTube"}],"brandName":"Takoon","name":"Zenith"},{"website":"https:\/\/element-kiteboarding.com\/product\/freefly\/","reviews":[],"imageFilename":"freefly.jpg","sizes":[{"areaSqM":3.8,"listPriceUSD":980,"doubleSkin":false},{"areaSqM":2.8,"listPriceUSD":919,"doubleSkin":false}],"discontinued":false,"videos":[],"brandName":"Element","name":"Freefly"},{"freshlyAdded":true,"reviews":[],"imageFilename":"Screen-Shot-2025-02-24-at-11.40.23-AM.png","sizes":[{"areaSqM":6,"listPriceUSD":1129,"doubleSkin":false},{"areaSqM":5,"listPriceUSD":1079,"doubleSkin":false},{"areaSqM":4,"listPriceUSD":1029,"doubleSkin":false},{"areaSqM":3,"listPriceUSD":979,"doubleSkin":false},{"areaSqM":2,"listPriceUSD":929,"doubleSkin":false}],"videos":[],"brandName":"Duotone","name":"Stash"},{"website":"https:\/\/www.f-one.world\/product\/frigate\/","reviews":[{"stars":5,"text":"Goes upwind great, a bit big to stash. The 4 is reaaaaally good.","date":"2025-12-19","userName":"nilsmango","website":"https:\/\/nilsmango.ch"}],"imageFilename":"frigate-2-650x650.png","sizes":[{"areaSqM":4.7,"weightKg":0.73,"doubleSkin":false},{"areaSqM":4,"doubleSkin":false},{"areaSqM":3,"doubleSkin":false}],"discontinued":false,"videos":[],"brandName":"F-ONE","name":"FRIGATE"}]